starship/__init__.py
starship-0.1.0.dist-info/LICENSE.txt
starship-0.1.0.dist-info/WHEEL
starship-0.1.0.dist-info/METADATA
starship-0.1.0.dist-info/RECORD
